dummy_validator/__init__.py
dummy_validator/base.py
dummy_validator/rules.py
dummy_validator-0.0.3.dist-info/METADATA
dummy_validator-0.0.3.dist-info/RECORD
dummy_validator-0.0.3.dist-info/WHEEL
dummy_validator-0.0.3.dist-info/entry_points.txt
dummy_validator-0.0.3.dist-info/top_level.txt
